dbt_unity_lineage/__init__.py
dbt_unity_lineage/cli.py
dbt_unity_lineage/config.py
dbt_unity_lineage/errors.py
dbt_unity_lineage/mapping.py
dbt_unity_lineage/profiles.py
dbt_unity_lineage/scanner.py
dbt_unity_lineage/unity_catalog.py
dbt_unity_lineage-0.3.1.dist-info/METADATA
dbt_unity_lineage-0.3.1.dist-info/WHEEL
dbt_unity_lineage-0.3.1.dist-info/entry_points.txt
dbt_unity_lineage-0.3.1.dist-info/licenses/LICENSE
dbt_unity_lineage-0.3.1.dist-info/RECORD
