Metadata-Version: 2.4
Name: dbt-unity-lineage
Version: 0.3.1
Summary: Push dbt lineage to Databricks Unity Catalog
Project-URL: Homepage, https://github.com/dbt-conceptual/dbt-unity-lineage
Project-URL: Documentation, https://github.com/dbt-conceptual/dbt-unity-lineage#readme
Project-URL: Repository, https://github.com/dbt-conceptual/dbt-unity-lineage
Project-URL: Issues, https://github.com/dbt-conceptual/dbt-unity-lineage/issues
Author: dbt-unity-lineage contributors
License-Expression: MIT
License-File: LICENSE
Keywords: databricks,dbt,lineage,unity-catalog
Classifier: Development Status :: 3 - Alpha
Classifier: Intended Audience :: Developers
Classifier: License :: OSI Approved :: MIT License
Classifier: Programming Language :: Python :: 3
Classifier: Programming Language :: Python :: 3.9
Classifier: Programming Language :: Python :: 3.10
Classifier: Programming Language :: Python :: 3.11
Classifier: Programming Language :: Python :: 3.12
Requires-Python: >=3.9
Requires-Dist: click>=8.0
Requires-Dist: databricks-sdk>=0.20.0
Requires-Dist: pydantic>=2.0
Requires-Dist: pyyaml>=6.0
Requires-Dist: rich>=13.0
Provides-Extra: dev
Requires-Dist: black>=23.0; extra == 'dev'
Requires-Dist: fastapi>=0.100.0; extra == 'dev'
Requires-Dist: httpx>=0.24.0; extra == 'dev'
Requires-Dist: mypy>=1.0; extra == 'dev'
Requires-Dist: pytest-cov>=4.0; extra == 'dev'
Requires-Dist: pytest>=7.0; extra == 'dev'
Requires-Dist: requests>=2.28.0; extra == 'dev'
Requires-Dist: ruff>=0.1.0; extra == 'dev'
Requires-Dist: uvicorn>=0.22.0; extra == 'dev'
